here_debugger/__init__.py
here_debugger/debug.py
here_debugger-2.0.0.dist-info/LICENSE
here_debugger-2.0.0.dist-info/METADATA
here_debugger-2.0.0.dist-info/WHEEL
here_debugger-2.0.0.dist-info/top_level.txt
here_debugger-2.0.0.dist-info/RECORD
