Metadata-Version: 2.1
Name: here_debugger
Version: 2.0.0
Summary: A user friendly debugger, just like print statement, but much more.
Home-page: https://github.com/Bibhash7/Here-Debugger
Author: Bibhash Ghosh
Author-email: tranceispermanemt@gmail.com
Project-URL: Bug Tracker, https://github.com/Bibhash7/Here-Debugger/issues
Classifier: Programming Language :: Python :: 3
Classifier: License :: OSI Approved :: MIT License
Classifier: Operating System :: OS Independent
Requires-Python: >=3.6
License-File: LICENSE
